probo/__init__.py
probo/utility.py
probo/components/__init__.py
probo/components/attributes.py
probo/components/base.py
probo/components/component.py
probo/components/elements.py
probo/components/node.py
probo/components/forms/__init__.py
probo/components/forms/probo_form.py
probo/components/state/__init__.py
probo/components/state/component_state.py
probo/components/state/props.py
probo/components/tag_classes/__init__.py
probo/components/tag_classes/block_tags.py
probo/components/tag_classes/self_closing.py
probo/components/tag_functions/__init__.py
probo/components/tag_functions/block_tags.py
probo/components/tag_functions/self_closing.py
probo/context/__init__.py
probo/context/context_logic.py
probo/context/django.py
probo/htmx/__init__.py
probo/htmx/htmx.py
probo/htmx/htmx_enum.py
probo/request/__init__.py
probo/request/props.py
probo/request/request_context.py
probo/request/transformer.py
probo/shortcuts/__init__.py
probo/shortcuts/configs.py
probo/shortcuts/shortcuts.py
probo/shortcuts/shortcuts_utils.py
probo/styles/__init__.py
probo/styles/css_enum.py
probo/styles/elements.py
probo/styles/plain_css.py
probo/styles/utils.py
probo/styles/frameworks/__init__.py
probo/styles/frameworks/bs5/__init__.py
probo/styles/frameworks/bs5/bs5.py
probo/styles/frameworks/bs5/comp_enum.py
probo/styles/frameworks/bs5/forms.py
probo/styles/frameworks/bs5/layout.py
probo/styles/frameworks/bs5/typography.py
probo/styles/frameworks/bs5/utilities.py
probo/styles/frameworks/bs5/components/__init__.py
probo/styles/frameworks/bs5/components/accordion.py
probo/styles/frameworks/bs5/components/alert.py
probo/styles/frameworks/bs5/components/badge.py
probo/styles/frameworks/bs5/components/base.py
probo/styles/frameworks/bs5/components/breadcrumb.py
probo/styles/frameworks/bs5/components/button.py
probo/styles/frameworks/bs5/components/card.py
probo/styles/frameworks/bs5/components/carousel.py
probo/styles/frameworks/bs5/components/collapse.py
probo_ui-1.2.0.dist-info/METADATA
probo_ui-1.2.0.dist-info/WHEEL
probo_ui-1.2.0.dist-info/entry_points.txt
probo_ui-1.2.0.dist-info/licenses/LICENSE
probo_ui-1.2.0.dist-info/RECORD
